Metadata-Version: 2.1
Name: turbosms
Version: 0.0.2
Summary: Turbosms python integration app
Home-page: https://github.com/pmaigutyak/mp-turbosms
Author: Paul Maigutyak
Author-email: pmaigutyak@gmail.com
License: MIT
Download-URL: https://github.com/pmaigutyak/mp-turbosms/archive/0.0.2.tar.gz
Platform: UNKNOWN
